visdet/__init__.py
visdet/registry.py
visdet/version.py
visdet/apis/__init__.py
visdet/apis/det_inferencer.py
visdet/apis/inference.py
visdet/configs/__init__.py
visdet/configs/_base_/default_runtime.py
visdet/configs/_base_/datasets/coco_instance.py
visdet/configs/_base_/models/cascade-mask-rcnn_r50_fpn.py
visdet/configs/_base_/models/mask-rcnn_r50_fpn.py
visdet/configs/_base_/schedules/schedule_1x.py
visdet/configs/swin/cascade-mask-rcnn_swin-s-p4-w7_fpn_ms-crop-3x_coco.py
visdet/configs/swin/mask-rcnn_swin-s-p4-w7_fpn_amp-ms-crop-3x_coco.py
visdet/configs/swin/mask-rcnn_swin-t-p4-w7_fpn_amp-ms-crop-3x_coco.py
visdet/configs/swin/mask-rcnn_swin-t-p4-w7_fpn_ms-crop-3x_coco.py
visdet/configs/swin/metafile.yml
visdet/datasets/__init__.py
visdet/datasets/base_det_dataset.py
visdet/datasets/coco.py
visdet/datasets/api_wrappers/__init__.py
visdet/datasets/api_wrappers/coco_api.py
visdet/datasets/api_wrappers/cocoeval_mp.py
visdet/datasets/samplers/__init__.py
visdet/datasets/samplers/class_aware_sampler.py
visdet/datasets/transforms/__init__.py
visdet/datasets/transforms/formatting.py
visdet/datasets/transforms/load_image.py
visdet/datasets/transforms/loading.py
visdet/datasets/transforms/transforms.py
visdet/engine/__init__.py
visdet/engine/hooks/__init__.py
visdet/engine/hooks/visualization_hook.py
visdet/engine/optimizers/__init__.py
visdet/evaluation/__init__.py
visdet/evaluation/evaluator/__init__.py
visdet/evaluation/functional/__init__.py
visdet/evaluation/functional/bbox_overlaps.py
visdet/evaluation/functional/class_names.py
visdet/evaluation/functional/mean_ap.py
visdet/evaluation/functional/panoptic_utils.py
visdet/evaluation/functional/recall.py
visdet/evaluation/metrics/__init__.py
visdet/evaluation/metrics/coco_metric.py
visdet/models/__init__.py
visdet/models/utils.py
visdet/models/backbones/__init__.py
visdet/models/backbones/swin.py
visdet/models/data_preprocessors/__init__.py
visdet/models/data_preprocessors/data_preprocessor.py
visdet-2.28.4.dist-info/METADATA
visdet-2.28.4.dist-info/WHEEL
visdet-2.28.4.dist-info/licenses/LICENSE
visdet-2.28.4.dist-info/RECORD
