Metadata-Version: 2.4
Name: visdet
Version: 2.28.4
Summary: Visia's fork of MMDetection - Object Detection Toolbox and Benchmark
Project-URL: Homepage, https://binitai.github.io/visdet/
Project-URL: Repository, https://github.com/BinItAI/visdet
Project-URL: Documentation, https://binitai.github.io/visdet/
Project-URL: Original Project, https://github.com/open-mmlab/mmdetection
Author-email: George Pearse <george@visia.ai>, MMDetection Contributors <openmmlab@gmail.com>
License: Apache License 2.0
License-File: LICENSE
Keywords: computer vision,mmdetection,object detection
Classifier: Development Status :: 5 - Production/Stable
Classifier: License :: OSI Approved :: Apache Software License
Classifier: Operating System :: OS Independent
Classifier: Programming Language :: Python :: 3
Classifier: Programming Language :: Python :: 3.10
Classifier: Programming Language :: Python :: 3.11
Classifier: Programming Language :: Python :: 3.12
Requires-Python: <3.13,>=3.10
Requires-Dist: matplotlib
Requires-Dist: numpy
Requires-Dist: pycocotools
Requires-Dist: scipy
Requires-Dist: six
Requires-Dist: terminaltables
Requires-Dist: tqdm>=4.67.1
Provides-Extra: albu
Requires-Dist: albumentations>=0.3.2; extra == 'albu'
Provides-Extra: all
Requires-Dist: albumentations>=0.3.2; extra == 'all'
Requires-Dist: cityscapesscripts; extra == 'all'
Requires-Dist: imagecorruptions; extra == 'all'
Requires-Dist: scikit-learn; extra == 'all'
Provides-Extra: mim
Requires-Dist: openmim; extra == 'mim'
Provides-Extra: mkdocs
Requires-Dist: mkdocs-gen-files>=0.5.0; extra == 'mkdocs'
Requires-Dist: mkdocs-git-revision-date-localized-plugin>=1.2.0; extra == 'mkdocs'
Requires-Dist: mkdocs-literate-nav>=0.6.0; extra == 'mkdocs'
Requires-Dist: mkdocs-material>=9.0.0; extra == 'mkdocs'
Requires-Dist: mkdocs-section-index>=0.3.0; extra == 'mkdocs'
Requires-Dist: mkdocs>=1.5.0; extra == 'mkdocs'
Requires-Dist: mkdocstrings[python]>=0.24.0; extra == 'mkdocs'
Provides-Extra: optional
Requires-Dist: cityscapesscripts; extra == 'optional'
Requires-Dist: imagecorruptions; extra == 'optional'
Requires-Dist: scikit-learn; extra == 'optional'
Provides-Extra: tests
Requires-Dist: asynctest; extra == 'tests'
Requires-Dist: codecov; extra == 'tests'
Requires-Dist: flake8; extra == 'tests'
Requires-Dist: interrogate; extra == 'tests'
Requires-Dist: isort==4.3.21; extra == 'tests'
Requires-Dist: kwarray; extra == 'tests'
Requires-Dist: onnx==1.7.0; extra == 'tests'
Requires-Dist: onnxruntime>=1.8.0; extra == 'tests'
Requires-Dist: protobuf<=3.20.1; extra == 'tests'
Requires-Dist: pytest; extra == 'tests'
Requires-Dist: pytest-cov; extra == 'tests'
Requires-Dist: ubelt; extra == 'tests'
Requires-Dist: xdoctest>=0.10.0; extra == 'tests'
Requires-Dist: yapf; extra == 'tests'
